{
	"sprites": [
		{
			"name": "all-0",
			"position": {
				"x": 0,
				"y": 0,
				"w": 64,
				"h": 64
			}
		}, 
		{
			"name": "all-1",
			"position": {
				"x": 65,
				"y": 0,
				"w": 64,
				"h": 64
			}
		}, 
		{
			"name": "all-2",
			"position": {
				"x": 130,
				"y": 0,
				"w": 64,
				"h": 64
			}
		}, 
		{
			"name": "all-3",
			"position": {
				"x": 195,
				"y": 0,
				"w": 64,
				"h": 64
			}
		}, 
		{
			"name": "all-4",
			"position": {
				"x": 260,
				"y": 0,
				"w": 64,
				"h": 64
			}
		}, 
		{
			"name": "all-5",
			"position": {
				"x": 0,
				"y": 65,
				"w": 64,
				"h": 64
			}
		}, 
		{
			"name": "all-6",
			"position": {
				"x": 65,
				"y": 65,
				"w": 64,
				"h": 64
			}
		}, 
		{
			"name": "all-7",
			"position": {
				"x": 130,
				"y": 65,
				"w": 64,
				"h": 64
			}
		}, 
		{
			"name": "all-8",
			"position": {
				"x": 195,
				"y": 65,
				"w": 64,
				"h": 64
			}
		}, 
		{
			"name": "all-9",
			"position": {
				"x": 260,
				"y": 65,
				"w": 64,
				"h": 64
			}
		},
		{
			"name": "all-10",
			"position": {
			"x": 0,
			"y": 130,
			"w": 64,
			"h": 64
			}
		},
		{
			"name": "all-11",
			"position": {
			"x": 65,
			"y": 130,
			"w": 64,
			"h": 64
			}
		},
		{
			"name": "all-12",
			"position": {
			"x": 130,
			"y": 130,
			"w": 64,
			"h": 64
			}
		},
		{
			"name": "all-13",
			"position": {
			"x": 195,
			"y": 130,
			"w": 64,
			"h": 64
			}
		},
		{
			"name": "all-14",
			"position": {
			"x": 260,
			"y": 130,
			"w": 64,
			"h": 64
			}
		},
		{
			"name": "all-15",
			"position": {
			"x": 0,
			"y": 195,
			"w": 64,
			"h": 64
			}
		},
		{
			"name": "all-16",
			"position": {
			"x": 65,
			"y": 195,
			"w": 64,
			"h": 64
			}
		},
		{
			"name": "all-17",
			"position": {
			"x": 130,
			"y": 195,
			"w": 64,
			"h": 64
			}
		},
		{
			"name": "all-18",
			"position": {
			"x": 195,
			"y": 195,
			"w": 64,
			"h": 64
			}
		},
		{
			"name": "all-19",
			"position": {
			"x": 260,
			"y": 195,
			"w": 64,
			"h": 64
			}
		},
		{
			"name": "all-20",
			"position": {
			"x": 0,
			"y": 260,
			"w": 64,
			"h": 64
			}
		},
		{
			"name": "all-21",
			"position": {
			"x": 65,
			"y": 260,
			"w": 64,
			"h": 64
			}
		},
		{
			"name": "all-22",
			"position": {
			"x": 130,
			"y": 260,
			"w": 64,
			"h": 64
			}
		},
		{
			"name": "all-23",
			"position": {
			"x": 195,
			"y": 260,
			"w": 64,
			"h": 64
			}
		},
		{
			"name": "all-24",
			"position": {
			"x": 260,
			"y": 260,
			"w": 64,
			"h": 64
			}
		},
		{
			"name": "all-25",
			"position": {
			"x": 0,
			"y": 325,
			"w": 64,
			"h": 64
			}
		},
		{
			"name": "all-26",
			"position": {
			"x": 65,
			"y": 325,
			"w": 64,
			"h": 64
			}
		},
		{
			"name": "all-27",
			"position": {
			"x": 130,
			"y": 325,
			"w": 64,
			"h": 64
			}
		},
		{
			"name": "all-28",
			"position": {
			"x": 195,
			"y": 325,
			"w": 64,
			"h": 64
			}
		},
		{
			"name": "all-29",
			"position": {
			"x": 260,
			"y": 325,
			"w": 64,
			"h": 64
			}
		},
		{
			"name": "all-30",
			"position": {
			"x": 0,
			"y": 390,
			"w": 64,
			"h": 64
			}
		},
		{
			"name": "all-31",
			"position": {
			"x": 65,
			"y": 390,
			"w": 64,
			"h": 64
			}
		},
		{
			"name": "all-32",
			"position": {
			"x": 130,
			"y": 390,
			"w": 64,
			"h": 64
			}
		},
		{
			"name": "all-33",
			"position": {
			"x": 195,
			"y": 390,
			"w": 64,
			"h": 64
			}
		},
		{
			"name": "all-34",
			"position": {
			"x": 260,
			"y": 390,
			"w": 64,
			"h": 64
			}
		},
		{
			"name": "all-35",
			"position": {
			"x": 0,
			"y": 455,
			"w": 64,
			"h": 64
			}
		},
		{
			"name": "all-36",
			"position": {
			"x": 65,
			"y": 455,
			"w": 64,
			"h": 64
			}
		},
		{
			"name": "barrel",
			"position": {
			"x": 130,
			"y": 455,
			"w": 64,
			"h": 64
			}
		},
		{
			"name": "all-38",
			"position": {
			"x": 195,
			"y": 455,
			"w": 64,
			"h": 64
			}
		},
		{
			"name": "all-39",
			"position": {
			"x": 260,
			"y": 455,
			"w": 64,
			"h": 64
			}
		},
		{
			"name": "all-40",
			"position": {
			"x": 0,
			"y": 520,
			"w": 64,
			"h": 64
			}
		},
		{
			"name": "all-41",
			"position": {
			"x": 65,
			"y": 520,
			"w": 64,
			"h": 64
			}
		},
		{
			"name": "all-42",
			"position": {
			"x": 130,
			"y": 520,
			"w": 64,
			"h": 64
			}
		},
		{
			"name": "all-43",
			"position": {
			"x": 195,
			"y": 520,
			"w": 64,
			"h": 64
			}
		},
		{
			"name": "all-44",
			"position": {
			"x": 260,
			"y": 520,
			"w": 64,
			"h": 64
			}
		},
		{
			"name": "all-45",
			"position": {
			"x": 0,
			"y": 585,
			"w": 64,
			"h": 64
			}
		},
		{
			"name": "all-46",
			"position": {
			"x": 65,
			"y": 585,
			"w": 64,
			"h": 64
			}
		},
		{
			"name": "all-47",
			"position": {
			"x": 130,
			"y": 585,
			"w": 64,
			"h": 64
			}
		},
		{
			"name": "all-48",
			"position": {
			"x": 195,
			"y": 585,
			"w": 64,
			"h": 64
			}
		},
		{
			"name": "all-49",
			"position": {
			"x": 260,
			"y": 585,
			"w": 64,
			"h": 64
			}
		}
	]
}